README.md
setup.cfg
setup.py
Alvaro.egg-info/PKG-INFO
Alvaro.egg-info/SOURCES.txt
Alvaro.egg-info/dependency_links.txt
Alvaro.egg-info/top_level.txt
alvaro/__init__.py
alvaro/__version__.py
alvaro/alvaro.py