Metadata-Version: 2.1
Name: Alvaro
Version: 1.0.4
Summary: Easy to use networking library.
Home-page: https://github.com/edgecase963/Alvaro
Author: edgecase963
Author-email: edgecase963@gmail.com
License: MIT
Platform: UNKNOWN
Classifier: License :: OSI Approved :: MIT License
Classifier: Programming Language :: Python
Classifier: Programming Language :: Python :: 3
Classifier: Programming Language :: Python :: 3.8
Classifier: Programming Language :: Python :: Implementation :: CPython
Classifier: Programming Language :: Python :: Implementation :: PyPy
Requires-Python: >=3.8.0
